verilog/ex2/simpleALU.v
`timescale 1 ns/ 1 ns

module alu (src_a, src_b, c, data_out);

input [7:0] src_a, src_b;
input [2:0] c;
output [7:0] data_out;

reg [7:0] data_out;

always @( c or src_a or src_b ) begin
    case (c)
        3'b001: data_out = src_a + src_b; // ADD
        3'b010: data_out = src_a - src_b; // SUB
        3'b011: data_out = src_a & src_b; // AND
        3'b100: data_out = src_a | src_b; // OR
        3'b101: data_out = src_a ^ src_b; // XOR
        default: data_out = src_a;
    endcase
end

endmodule

verilog/ex2/t_simpleALU.v
// Code your testbench here
// or browse Examples
`timescale 1 ns/1 ns

module testbench;
reg [7:0] src_a, src_b;
reg [2:0] c;
wire [7:0] data_out;

alu ALU_instance(.src_a(src_a), .src_b(src_b), .c(c), .data_out(data_out) );

initial
begin

  $dumpfile("simpleALU.vcd");
  $dumpvars;

  src_a = 8'h55;  // Time = 0
  src_b = 8'h1a;
  c	= 3'b000;
  #50;		  // Time = 50
  c	= 3'b001; 
  #50;		  // Time = 100 
  c	= 3'b010; 
  #50;		  // Time = 150 
  c	= 3'b011; 
  #50;		  // Time = 200 
  c	= 3'b100; 
  #50;		  // Time = 250 
  c	= 3'b101; 
  #50;		  // Time = 300 
  c	= 3'b110; 
  #50;		  // Time = 350
  c	= 3'b111; 
 
end
  
always #50 begin
  $monitor("time: %8d, a:%d, b:%d, c:%d, d_out:%d",$time, src_a, src_b, c,data_out);
end

initial #400 $finish;
endmodule

verilog/ex2/simpleALU.vcd
$date
	Wed Oct 31 16:17:31 2018
$end
$version
	Icarus Verilog
$end
$timescale
	1ns
$end
$scope module testbench $end
$var wire 8 ! data_out [7:0] $end
$var reg 3 " c [2:0] $end
$var reg 8 # src_a [7:0] $end
$var reg 8 $ src_b [7:0] $end
$scope module ALU_instance $end
$var wire 3 % c [2:0] $end
$var wire 8 & src_a [7:0] $end
$var wire 8 ' src_b [7:0] $end
$var reg 8 ( data_out [7:0] $end
$upscope $end
$upscope $end
$enddefinitions $end
#0
$dumpvars
b1010101 (
b11010 '
b1010101 &
b0 %
b11010 $
b1010101 #
b0 "
b1010101 !
$end
#50
b1101111 !
b1101111 (
b1 "
b1 %
#100
b111011 !
b111011 (
b10 "
b10 %
#150
b10000 !
b10000 (
b11 "
b11 %
#200
b1011111 !
b1011111 (
b100 "
b100 %
#250
b1001111 !
b1001111 (
b101 "
b101 %
#300
b1010101 !
b1010101 (
b110 "
b110 %
#350
b111 "
b111 %
